pocomc/__init__.py
pocomc/_version.py
pocomc/flow.py
pocomc/geometry.py
pocomc/input_validation.py
pocomc/mcmc.py
pocomc/parallel.py
pocomc/particles.py
pocomc/prior.py
pocomc/sampler.py
pocomc/scaler.py
pocomc/student.py
pocomc/threading.py
pocomc/tools.py
pocomc-1.2.6.dist-info/LICENCE
pocomc-1.2.6.dist-info/METADATA
pocomc-1.2.6.dist-info/WHEEL
pocomc-1.2.6.dist-info/top_level.txt
pocomc-1.2.6.dist-info/RECORD
