Metadata-Version: 2.1
Name: pocomc
Version: 1.2.6
Summary: Preconditioned Monte Carlo
Home-page: https://github.com/minaskar/pocomc
Author: Minas Karamanis
Author-email: minaskar@gmail.com
License: GPLv3
Platform: any
Classifier: Programming Language :: Python :: 3
Classifier: License :: OSI Approved :: GNU General Public License v3 (GPLv3)
Classifier: Operating System :: OS Independent
Classifier: Intended Audience :: Science/Research
Classifier: Topic :: Scientific/Engineering
Classifier: Topic :: Scientific/Engineering :: Mathematics
Requires-Python: >=3.8
License-File: LICENCE
Requires-Dist: numpy >=1.20.0
Requires-Dist: torch >=1.12.0
Requires-Dist: zuko >=1.1.0
Requires-Dist: tqdm >=4.60.0
Requires-Dist: scipy >=1.4.0
Requires-Dist: dill >=0.3.8
Requires-Dist: multiprocess >=0.70.15
